emiproc/__init__.py
emiproc/__main__.py
emiproc/_version.py
emiproc/grids.py
emiproc/human_respiration.py
emiproc/regrid.py
emiproc/speciation.py
emiproc/utilities.py
emiproc/exports/__init__.py
emiproc/exports/fluxy.py
emiproc/exports/gral.py
emiproc/exports/hourly.py
emiproc/exports/icon.py
emiproc/exports/netcdf.py
emiproc/exports/profiles.py
emiproc/exports/rasters.py
emiproc/exports/utils.py
emiproc/exports/wrf.py
emiproc/inventories/__init__.py
emiproc/inventories/cams_reg_aq.py
emiproc/inventories/categories_groups.py
emiproc/inventories/gfas.py
emiproc/inventories/gfed.py
emiproc/inventories/gral.py
emiproc/inventories/lpjguess.py
emiproc/inventories/netcdf_raster.py
emiproc/inventories/saunois.py
emiproc/inventories/swiss.py
emiproc/inventories/tno.py
emiproc/inventories/utils.py
emiproc/inventories/wetcharts.py
emiproc/inventories/zurich.py
emiproc/inventories/edgar/__init__.py
emiproc/inventories/edgar/edgarv8.py
emiproc/inventories/edgar/temporal.py
emiproc/inventories/zurich/__init__.py
emiproc/inventories/zurich/categories_info.py
emiproc/inventories/zurich/duck.py
emiproc/inventories/zurich/gnrf_groups.py
emiproc/inventories/zurich/gral_groups.py
emiproc/inventories/zurich/speciation_co2_bio.py
emiproc/plots/__init__.py
emiproc/plots/nclcmaps.py
emiproc/plots/vprm.py
emiproc/profiles/__init__.py
emiproc/profiles/hdd.py
emiproc/profiles/naming.py
emiproc/profiles/operators.py
emiproc/profiles/plot.py
emiproc/profiles/temporal_profiles.py
emiproc/profiles/utils.py
emiproc/profiles/vertical_profiles.py
emiproc/profiles/vprm.py
emiproc/profiles/temporal/__init__.py
emiproc/profiles/temporal/composite.py
emiproc/profiles/temporal/constants.py
emiproc/profiles/temporal/io.py
emiproc/profiles/temporal/operators.py
emiproc/profiles/temporal/profiles.py
emiproc/profiles/temporal/specific_days.py
emiproc/profiles/temporal/utils.py
emiproc/tests_utils/__init__.py
emiproc/tests_utils/african_case.py
emiproc/tests_utils/exports.py
emiproc/tests_utils/icon.py
emiproc-2.7.0.dist-info/licenses/LICENSE.txt
emiproc-2.7.0.dist-info/METADATA
emiproc-2.7.0.dist-info/WHEEL
emiproc-2.7.0.dist-info/top_level.txt
emiproc-2.7.0.dist-info/RECORD
