Metadata-Version: 2.4
Name: emiproc
Version: 2.7.0
Summary: Emission Processing Tool
Author: Michael Jähn, Gerrit Kuhlmann, Qing Mu, Jean-Matthieu Haussaire, David Ochsner, Katherine Osterried, Valentin Clément, Joel Thanwerdas, Corina Keller, Erik Koene, Alessandro Bigi, Michael Steiner
Author-email: Lionel Constantin <lionel.constantin@empa.ch>, Dominik Brunner <dominik.brunner@empa.ch>
License: BSD-3-Clause
Keywords: emission,processing,inventory,cosmo,icon-art
Classifier: Programming Language :: Python :: 3
Requires-Python: >=3.10
License-File: LICENSE.txt
Requires-Dist: geos
Requires-Dist: numpy
Requires-Dist: pandas
Requires-Dist: geopandas
Requires-Dist: netCDF4
Requires-Dist: dask
Requires-Dist: scipy
Requires-Dist: shapely
Requires-Dist: xarray>=2023.10
Requires-Dist: rasterio
Requires-Dist: pyogrio
Requires-Dist: pyyaml
Requires-Dist: filelock
Provides-Extra: doc
Requires-Dist: sphinx; extra == "doc"
Requires-Dist: furo; extra == "doc"
Requires-Dist: enum-tools; extra == "doc"
Requires-Dist: sphinx_toolbox; extra == "doc"
Requires-Dist: nbsphinx; extra == "doc"
Requires-Dist: ipython; extra == "doc"
Requires-Dist: matplotlib; extra == "doc"
Provides-Extra: dev
Requires-Dist: black; extra == "dev"
Requires-Dist: pytest; extra == "dev"
Dynamic: license-file
